PyTado/__init__.py
PyTado/__main__.py
PyTado/interface.py
python_tadoac-0.0.2.dist-info/AUTHORS
python_tadoac-0.0.2.dist-info/LICENSE
python_tadoac-0.0.2.dist-info/METADATA
python_tadoac-0.0.2.dist-info/WHEEL
python_tadoac-0.0.2.dist-info/entry_points.txt
python_tadoac-0.0.2.dist-info/top_level.txt
python_tadoac-0.0.2.dist-info/RECORD
